ReconRaccoon/__init__.py
ReconRaccoon/entry.py
ReconRaccoon/reconraccoon.py
ReconRaccoon/src/__init__.py
ReconRaccoon/src/framework/__init__.py
ReconRaccoon/src/framework/cli.py
ReconRaccoon/src/framework/functions.py
ReconRaccoon/src/modules/__init__.py
ReconRaccoon/src/modules/crawl/__init__.py
ReconRaccoon/src/modules/crawl/main.py
ReconRaccoon/src/modules/resolve/__init__.py
ReconRaccoon/src/modules/resolve/main.py
ReconRaccoon/src/modules/shcheck/__init__.py
ReconRaccoon/src/modules/shcheck/main.py
ReconRaccoon/src/modules/template/__init__.py
ReconRaccoon/src/modules/template/main.py
ReconRaccoon-1.1.0.dist-info/LICENSE
ReconRaccoon-1.1.0.dist-info/METADATA
ReconRaccoon-1.1.0.dist-info/WHEEL
ReconRaccoon-1.1.0.dist-info/entry_points.txt
ReconRaccoon-1.1.0.dist-info/top_level.txt
ReconRaccoon-1.1.0.dist-info/RECORD
