Metadata-Version: 2.1
Name: ReconRaccoon
Version: 1.1.0
Summary: Web Security Testing Framework
Home-page: https://github.com/whatev33r/ReconRaccoon
Author: whatev33r
Requires-Python: >=3
License-File: LICENSE
Requires-Dist: requests ==2.31.0
Requires-Dist: urllib3 ==1.26.15
